Workbook

Sheet How to Use
A1: How to Use This Workbook
A3: This workbook analyzes whether a project is worth taking. It calculates your expected profit, factors in the time value of money, and tells you if the job is a GO or NO-GO.
A5: Go to the Assumptions tab and update the yellow cells with your project details -- what you're charging, your costs, and the timeline. As the project runs, enter your actual costs in the blue cells on the Cash Flow tab. All results update automatically.
A7: Check the Summary tab for the bottom line: your project value, return rate, break-even month, and a GO/NO-GO recommendation. The Sensitivity tab shows how results change if costs or timelines shift.
A9: COLOR GUIDE
B10: YELLOW | C10: Your input -- fill these in
B11: BLUE | C11: Actual results -- enter as they come in
B12: GRAY | C12: Calculated -- don't touch
B13: GREEN | C13: Good result -- on track
B14: RED | C14: Needs attention -- action required

Sheet Summary
A1: =Assumptions!$B$5&" -- Project Returns Summary"
A2: Generated April 22, 2026
A4: THE BOTTOM LINE
A5: Project Value in Today's Dollars (NPV) | B5: ='Cash Flow'!AA23
A6: Annual Return on Investment (IRR) | B6: =IFERROR((1+IRR('Cash Flow'!B25:H25))^12-1,0)
A7: Profit After Direct Costs (Gross Margin) | B7: =Assumptions!$B$30
A8: Recommendation | B8: =IF(AND('Cash Flow'!AA23>0,Assumptions!$B$30>=Assumptions!$B$23),"GO -- This project is worth taking",IF('Cash Flow'!AA23>0,"MAYBE -- Positive returns but thin margins","NO-GO -- Review your assumptions"))
A10: PROJECT DETAILS
A11: Project | B11: =Assumptions!$B$6
A12: Customer | B12: =Assumptions!$B$7
A13: Company | B13: =Assumptions!$B$5
A14: Project Length | B14: =Assumptions!$B$9&" months"
A16: FINANCIAL SUMMARY
A17: What You're Charging (Contract Value) | B17: =Assumptions!$B$8
A18: Total Estimated Cost | B18: =Assumptions!$B$28
A19: Profit After Direct Costs (Gross Profit) | B19: =Assumptions!$B$29
A20: Profit Margin % (Gross Margin) | B20: =Assumptions!$B$30
A22: RETURNS DETAIL
A23: Project Value in Today's Dollars (NPV) | B23: ='Cash Flow'!AA23
A24: Monthly Return (IRR) | B24: =IFERROR(IRR('Cash Flow'!B25:H25),0)
A25: Annual Return (IRR) | B25: =IFERROR((1+IRR('Cash Flow'!B25:H25))^12-1,0)
A28: TRACKING YOUR PERFORMANCE (GOAL & CONTROL)
A29: Are You Hitting Labor Targets? (Labor Efficiency) | B29: =IFERROR(IF(COUNTA('Cash Flow'!C7:AB7)=0,"No actuals yet",SUM('Cash Flow'!C7:AB7)/SUM('Cash Flow'!B7:AA7)),"N/A")
A30: Is Your Margin Holding? (Margin Discipline) | B30: =IFERROR(Assumptions!$B$30/Assumptions!$B$23,"N/A")
A31: Is the Project Profitable? (NPV Status) | B31: =IF('Cash Flow'!AA23>0,"Positive -- proceed","Negative -- review assumptions")
A33: PAYMENT SCHEDULE (BILLING TERMS USED)
A34: Upfront | B34: =Assumptions!$B$19
A35: Monthly progress (spread) | B35: =1-Assumptions!$B$19-Assumptions!$B$20
A36: Retention (released at completion) | B36: =Assumptions!$B$20
A37: Verify against your signed contract terms.

Sheet Assumptions
A1: Verification Test LLC -- Project Returns: Assumptions
A2: Change any blue number and the entire model updates.
A4: PROJECT DETAILS
A5: Company Name | B5: Verification Test LLC
A6: Project Name | B6: Demo NPV Analysis
A7: Customer | B7: Demo Customer
A8: What You're Charging (Contract Value) | B8: 4250000
A9: Project Length in Months (Timeline) | B9: 6
A10: Cost of Money % (Discount Rate) | B10: 0.1
A12: YOUR COSTS (% OF CONTRACT)
A13: Labor % | B13: 0.3
A14: Materials % | B14: 0.25
A15: Subcontractors % | B15: 0.15
A16: Equipment % | B16: 0.03
A18: WHEN YOU GET PAID (BILLING)
A19: Upfront Payment % | B19: 0.1
A20: Holdback % (Retention) | B20: 0.1
A22: YOUR TARGETS (GOAL & CONTROL)
A23: Minimum Profit Margin (Target Gross Margin) | B23: 0.1
A24: How Far Off Is OK? (Variance Threshold) | B24: 0.03
A26: CALCULATED (DON'T CHANGE)
A27: Total Cost % | B27: =Assumptions!$B$13+Assumptions!$B$14+Assumptions!$B$15+Assumptions!$B$16
A28: Total Estimated Cost | B28: =Assumptions!$B$8*Assumptions!$B$27
A29: Profit After Direct Costs (Gross Profit) | B29: =Assumptions!$B$8-Assumptions!$B$28
A30: Profit Margin % (Gross Margin) | B30: =IF(Assumptions!$B$8=0,0,Assumptions!$B$29/Assumptions!$B$8)
A31: Upfront Amount | B31: =Assumptions!$B$8*Assumptions!$B$19
A32: Holdback Amount (Retention) | B32: =Assumptions!$B$8*Assumptions!$B$20
A33: Monthly Progress Billing | B33: =IF(Assumptions!$B$9=0,0,(Assumptions!$B$8-Assumptions!$B$31-Assumptions!$B$32)/Assumptions!$B$9)

Sheet Cash Flow
A1: =Assumptions!$B$5&" -- "&Assumptions!$B$6&": Cash Flow Schedule"
A2: Enter actuals in yellow cells. Variances calculate automatically.
B4: Month 1 | G4: Month 2 | L4: Month 3 | Q4: Month 4 | V4: Month 5 | AA4: Month 6
B5: Budget | C5: Actual | D5: Var $ | E5: Var % | F5: Status | G5: Budget | H5: Actual | I5: Var $ | J5: Var % | K5: Status | L5: Budget | M5: Actual | N5: Var $ | O5: Var % | P5: Status | Q5: Budget | R5: Actual | S5: Var $ | T5: Var % | U5: Status | V5: Budget | W5: Actual | X5: Var $ | Y5: Var % | Z5: Status | AA5: Budget | AB5: Actual | AC5: Var $ | AD5: Var % | AE5: Status
A6: CASH OUTFLOWS
A7: Labor | B7: =Assumptions!$B$8*Assumptions!$B$13/Assumptions!$B$9 | D7: =IF(C7="","",C7-B7) | E7: =IF(C7="","",IF(B7=0,0,(C7-B7)/ABS(B7))) | F7: =IF(C7="","",IF(E7<=0,"On Track",IF(E7<=Assumptions!$B$24,"Monitor","Action Needed"))) | G7: =Assumptions!$B$8*Assumptions!$B$13/Assumptions!$B$9 | I7: =IF(H7="","",H7-G7) | J7: =IF(H7="","",IF(G7=0,0,(H7-G7)/ABS(G7))) | K7: =IF(H7="","",IF(J7<=0,"On Track",IF(J7<=Assumptions!$B$24,"Monitor","Action Needed"))) | L7: =Assumptions!$B$8*Assumptions!$B$13/Assumptions!$B$9 | N7: =IF(M7="","",M7-L7) | O7: =IF(M7="","",IF(L7=0,0,(M7-L7)/ABS(L7))) | P7: =IF(M7="","",IF(O7<=0,"On Track",IF(O7<=Assumptions!$B$24,"Monitor","Action Needed"))) | Q7: =Assumptions!$B$8*Assumptions!$B$13/Assumptions!$B$9 | S7: =IF(R7="","",R7-Q7) | T7: =IF(R7="","",IF(Q7=0,0,(R7-Q7)/ABS(Q7))) | U7: =IF(R7="","",IF(T7<=0,"On Track",IF(T7<=Assumptions!$B$24,"Monitor","Action Needed"))) | V7: =Assumptions!$B$8*Assumptions!$B$13/Assumptions!$B$9 | X7: =IF(W7="","",W7-V7) | Y7: =IF(W7="","",IF(V7=0,0,(W7-V7)/ABS(V7))) | Z7: =IF(W7="","",IF(Y7<=0,"On Track",IF(Y7<=Assumptions!$B$24,"Monitor","Action Needed"))) | AA7: =Assumptions!$B$8*Assumptions!$B$13/Assumptions!$B$9 | AC7: =IF(AB7="","",AB7-AA7) | AD7: =IF(AB7="","",IF(AA7=0,0,(AB7-AA7)/ABS(AA7))) | AE7: =IF(AB7="","",IF(AD7<=0,"On Track",IF(AD7<=Assumptions!$B$24,"Monitor","Action Needed")))
A8: Materials | B8: =Assumptions!$B$8*Assumptions!$B$14/Assumptions!$B$9 | D8: =IF(C8="","",C8-B8) | E8: =IF(C8="","",IF(B8=0,0,(C8-B8)/ABS(B8))) | F8: =IF(C8="","",IF(E8<=0,"On Track",IF(E8<=Assumptions!$B$24,"Monitor","Action Needed"))) | G8: =Assumptions!$B$8*Assumptions!$B$14/Assumptions!$B$9 | I8: =IF(H8="","",H8-G8) | J8: =IF(H8="","",IF(G8=0,0,(H8-G8)/ABS(G8))) | K8: =IF(H8="","",IF(J8<=0,"On Track",IF(J8<=Assumptions!$B$24,"Monitor","Action Needed"))) | L8: =Assumptions!$B$8*Assumptions!$B$14/Assumptions!$B$9 | N8: =IF(M8="","",M8-L8) | O8: =IF(M8="","",IF(L8=0,0,(M8-L8)/ABS(L8))) | P8: =IF(M8="","",IF(O8<=0,"On Track",IF(O8<=Assumptions!$B$24,"Monitor","Action Needed"))) | Q8: =Assumptions!$B$8*Assumptions!$B$14/Assumptions!$B$9 | S8: =IF(R8="","",R8-Q8) | T8: =IF(R8="","",IF(Q8=0,0,(R8-Q8)/ABS(Q8))) | U8: =IF(R8="","",IF(T8<=0,"On Track",IF(T8<=Assumptions!$B$24,"Monitor","Action Needed"))) | V8: =Assumptions!$B$8*Assumptions!$B$14/Assumptions!$B$9 | X8: =IF(W8="","",W8-V8) | Y8: =IF(W8="","",IF(V8=0,0,(W8-V8)/ABS(V8))) | Z8: =IF(W8="","",IF(Y8<=0,"On Track",IF(Y8<=Assumptions!$B$24,"Monitor","Action Needed"))) | AA8: =Assumptions!$B$8*Assumptions!$B$14/Assumptions!$B$9 | AC8: =IF(AB8="","",AB8-AA8) | AD8: =IF(AB8="","",IF(AA8=0,0,(AB8-AA8)/ABS(AA8))) | AE8: =IF(AB8="","",IF(AD8<=0,"On Track",IF(AD8<=Assumptions!$B$24,"Monitor","Action Needed")))
A9: Subcontractors | B9: =Assumptions!$B$8*Assumptions!$B$15/Assumptions!$B$9 | D9: =IF(C9="","",C9-B9) | E9: =IF(C9="","",IF(B9=0,0,(C9-B9)/ABS(B9))) | F9: =IF(C9="","",IF(E9<=0,"On Track",IF(E9<=Assumptions!$B$24,"Monitor","Action Needed"))) | G9: =Assumptions!$B$8*Assumptions!$B$15/Assumptions!$B$9 | I9: =IF(H9="","",H9-G9) | J9: =IF(H9="","",IF(G9=0,0,(H9-G9)/ABS(G9))) | K9: =IF(H9="","",IF(J9<=0,"On Track",IF(J9<=Assumptions!$B$24,"Monitor","Action Needed"))) | L9: =Assumptions!$B$8*Assumptions!$B$15/Assumptions!$B$9 | N9: =IF(M9="","",M9-L9) | O9: =IF(M9="","",IF(L9=0,0,(M9-L9)/ABS(L9))) | P9: =IF(M9="","",IF(O9<=0,"On Track",IF(O9<=Assumptions!$B$24,"Monitor","Action Needed"))) | Q9: =Assumptions!$B$8*Assumptions!$B$15/Assumptions!$B$9 | S9: =IF(R9="","",R9-Q9) | T9: =IF(R9="","",IF(Q9=0,0,(R9-Q9)/ABS(Q9))) | U9: =IF(R9="","",IF(T9<=0,"On Track",IF(T9<=Assumptions!$B$24,"Monitor","Action Needed"))) | V9: =Assumptions!$B$8*Assumptions!$B$15/Assumptions!$B$9 | X9: =IF(W9="","",W9-V9) | Y9: =IF(W9="","",IF(V9=0,0,(W9-V9)/ABS(V9))) | Z9: =IF(W9="","",IF(Y9<=0,"On Track",IF(Y9<=Assumptions!$B$24,"Monitor","Action Needed"))) | AA9: =Assumptions!$B$8*Assumptions!$B$15/Assumptions!$B$9 | AC9: =IF(AB9="","",AB9-AA9) | AD9: =IF(AB9="","",IF(AA9=0,0,(AB9-AA9)/ABS(AA9))) | AE9: =IF(AB9="","",IF(AD9<=0,"On Track",IF(AD9<=Assumptions!$B$24,"Monitor","Action Needed")))
A10: Equipment | B10: =Assumptions!$B$8*Assumptions!$B$16/Assumptions!$B$9 | D10: =IF(C10="","",C10-B10) | E10: =IF(C10="","",IF(B10=0,0,(C10-B10)/ABS(B10))) | F10: =IF(C10="","",IF(E10<=0,"On Track",IF(E10<=Assumptions!$B$24,"Monitor","Action Needed"))) | G10: =Assumptions!$B$8*Assumptions!$B$16/Assumptions!$B$9 | I10: =IF(H10="","",H10-G10) | J10: =IF(H10="","",IF(G10=0,0,(H10-G10)/ABS(G10))) | K10: =IF(H10="","",IF(J10<=0,"On Track",IF(J10<=Assumptions!$B$24,"Monitor","Action Needed"))) | L10: =Assumptions!$B$8*Assumptions!$B$16/Assumptions!$B$9 | N10: =IF(M10="","",M10-L10) | O10: =IF(M10="","",IF(L10=0,0,(M10-L10)/ABS(L10))) | P10: =IF(M10="","",IF(O10<=0,"On Track",IF(O10<=Assumptions!$B$24,"Monitor","Action Needed"))) | Q10: =Assumptions!$B$8*Assumptions!$B$16/Assumptions!$B$9 | S10: =IF(R10="","",R10-Q10) | T10: =IF(R10="","",IF(Q10=0,0,(R10-Q10)/ABS(Q10))) | U10: =IF(R10="","",IF(T10<=0,"On Track",IF(T10<=Assumptions!$B$24,"Monitor","Action Needed"))) | V10: =Assumptions!$B$8*Assumptions!$B$16/Assumptions!$B$9 | X10: =IF(W10="","",W10-V10) | Y10: =IF(W10="","",IF(V10=0,0,(W10-V10)/ABS(V10))) | Z10: =IF(W10="","",IF(Y10<=0,"On Track",IF(Y10<=Assumptions!$B$24,"Monitor","Action Needed"))) | AA10: =Assumptions!$B$8*Assumptions!$B$16/Assumptions!$B$9 | AC10: =IF(AB10="","",AB10-AA10) | AD10: =IF(AB10="","",IF(AA10=0,0,(AB10-AA10)/ABS(AA10))) | AE10: =IF(AB10="","",IF(AD10<=0,"On Track",IF(AD10<=Assumptions!$B$24,"Monitor","Action Needed")))
A11: TOTAL OUTFLOWS | B11: =B7+B8+B9+B10 | C11: =IF(AND(C7<>"",C8<>"",C9<>"",C10<>""),C7+C8+C9+C10,"") | D11: =IF(C11="","",C11-B11) | E11: =IF(C11="","",IF(B11=0,0,(C11-B11)/ABS(B11))) | F11: =IF(C11="","",IF(E11<=0,"On Track",IF(E11<=Assumptions!$B$24,"Monitor","Action Needed"))) | G11: =G7+G8+G9+G10 | H11: =IF(AND(H7<>"",H8<>"",H9<>"",H10<>""),H7+H8+H9+H10,"") | I11: =IF(H11="","",H11-G11) | J11: =IF(H11="","",IF(G11=0,0,(H11-G11)/ABS(G11))) | K11: =IF(H11="","",IF(J11<=0,"On Track",IF(J11<=Assumptions!$B$24,"Monitor","Action Needed"))) | L11: =L7+L8+L9+L10 | M11: =IF(AND(M7<>"",M8<>"",M9<>"",M10<>""),M7+M8+M9+M10,"") | N11: =IF(M11="","",M11-L11) | O11: =IF(M11="","",IF(L11=0,0,(M11-L11)/ABS(L11))) | P11: =IF(M11="","",IF(O11<=0,"On Track",IF(O11<=Assumptions!$B$24,"Monitor","Action Needed"))) | Q11: =Q7+Q8+Q9+Q10 | R11: =IF(AND(R7<>"",R8<>"",R9<>"",R10<>""),R7+R8+R9+R10,"") | S11: =IF(R11="","",R11-Q11) | T11: =IF(R11="","",IF(Q11=0,0,(R11-Q11)/ABS(Q11))) | U11: =IF(R11="","",IF(T11<=0,"On Track",IF(T11<=Assumptions!$B$24,"Monitor","Action Needed"))) | V11: =V7+V8+V9+V10 | W11: =IF(AND(W7<>"",W8<>"",W9<>"",W10<>""),W7+W8+W9+W10,"") | X11: =IF(W11="","",W11-V11) | Y11: =IF(W11="","",IF(V11=0,0,(W11-V11)/ABS(V11))) | Z11: =IF(W11="","",IF(Y11<=0,"On Track",IF(Y11<=Assumptions!$B$24,"Monitor","Action Needed"))) | AA11: =AA7+AA8+AA9+AA10 | AB11: =IF(AND(AB7<>"",AB8<>"",AB9<>"",AB10<>""),AB7+AB8+AB9+AB10,"") | AC11: =IF(AB11="","",AB11-AA11) | AD11: =IF(AB11="","",IF(AA11=0,0,(AB11-AA11)/ABS(AA11))) | AE11: =IF(AB11="","",IF(AD11<=0,"On Track",IF(AD11<=Assumptions!$B$24,"Monitor","Action Needed")))
A13: CASH INFLOWS
A14: Progress Billing | B14: =Assumptions!$B$33+Assumptions!$B$31 | D14: =IF(C14="","",C14-B14) | E14: =IF(C14="","",IF(B14=0,0,(C14-B14)/ABS(B14))) | F14: =IF(C14="","",IF(E14>=0,"On Track",IF(E14>=-Assumptions!$B$24,"Monitor","Action Needed"))) | G14: =Assumptions!$B$33 | I14: =IF(H14="","",H14-G14) | J14: =IF(H14="","",IF(G14=0,0,(H14-G14)/ABS(G14))) | K14: =IF(H14="","",IF(J14>=0,"On Track",IF(J14>=-Assumptions!$B$24,"Monitor","Action Needed"))) | L14: =Assumptions!$B$33 | N14: =IF(M14="","",M14-L14) | O14: =IF(M14="","",IF(L14=0,0,(M14-L14)/ABS(L14))) | P14: =IF(M14="","",IF(O14>=0,"On Track",IF(O14>=-Assumptions!$B$24,"Monitor","Action Needed"))) | Q14: =Assumptions!$B$33 | S14: =IF(R14="","",R14-Q14) | T14: =IF(R14="","",IF(Q14=0,0,(R14-Q14)/ABS(Q14))) | U14: =IF(R14="","",IF(T14>=0,"On Track",IF(T14>=-Assumptions!$B$24,"Monitor","Action Needed"))) | V14: =Assumptions!$B$33 | X14: =IF(W14="","",W14-V14) | Y14: =IF(W14="","",IF(V14=0,0,(W14-V14)/ABS(V14))) | Z14: =IF(W14="","",IF(Y14>=0,"On Track",IF(Y14>=-Assumptions!$B$24,"Monitor","Action Needed"))) | AA14: =Assumptions!$B$33+Assumptions!$B$32 | AC14: =IF(AB14="","",AB14-AA14) | AD14: =IF(AB14="","",IF(AA14=0,0,(AB14-AA14)/ABS(AA14))) | AE14: =IF(AB14="","",IF(AD14>=0,"On Track",IF(AD14>=-Assumptions!$B$24,"Monitor","Action Needed")))
A16: NET CASH FLOW
A17: Net Cash Flow | B17: =B14-B11 | C17: =IF(OR(C14="",C11=""),"",C14-C11) | D17: =IF(C17="","",C17-B17) | E17: =IF(C17="","",IF(B17=0,0,(C17-B17)/ABS(B17))) | F17: =IF(C17="","",IF(E17>=0,"On Track",IF(E17>=-Assumptions!$B$24,"Monitor","Action Needed"))) | G17: =G14-G11 | H17: =IF(OR(H14="",H11=""),"",H14-H11) | I17: =IF(H17="","",H17-G17) | J17: =IF(H17="","",IF(G17=0,0,(H17-G17)/ABS(G17))) | K17: =IF(H17="","",IF(J17>=0,"On Track",IF(J17>=-Assumptions!$B$24,"Monitor","Action Needed"))) | L17: =L14-L11 | M17: =IF(OR(M14="",M11=""),"",M14-M11) | N17: =IF(M17="","",M17-L17) | O17: =IF(M17="","",IF(L17=0,0,(M17-L17)/ABS(L17))) | P17: =IF(M17="","",IF(O17>=0,"On Track",IF(O17>=-Assumptions!$B$24,"Monitor","Action Needed"))) | Q17: =Q14-Q11 | R17: =IF(OR(R14="",R11=""),"",R14-R11) | S17: =IF(R17="","",R17-Q17) | T17: =IF(R17="","",IF(Q17=0,0,(R17-Q17)/ABS(Q17))) | U17: =IF(R17="","",IF(T17>=0,"On Track",IF(T17>=-Assumptions!$B$24,"Monitor","Action Needed"))) | V17: =V14-V11 | W17: =IF(OR(W14="",W11=""),"",W14-W11) | X17: =IF(W17="","",W17-V17) | Y17: =IF(W17="","",IF(V17=0,0,(W17-V17)/ABS(V17))) | Z17: =IF(W17="","",IF(Y17>=0,"On Track",IF(Y17>=-Assumptions!$B$24,"Monitor","Action Needed"))) | AA17: =AA14-AA11 | AB17: =IF(OR(AB14="",AB11=""),"",AB14-AB11) | AC17: =IF(AB17="","",AB17-AA17) | AD17: =IF(AB17="","",IF(AA17=0,0,(AB17-AA17)/ABS(AA17))) | AE17: =IF(AB17="","",IF(AD17>=0,"On Track",IF(AD17>=-Assumptions!$B$24,"Monitor","Action Needed")))
A18: Cumulative Cash Flow | B18: =B17 | G18: =B18+G17 | L18: =G18+L17 | Q18: =L18+Q17 | V18: =Q18+V17 | AA18: =V18+AA17
A20: NPV ANALYSIS
A21: Time Value Factor (Discount) | B21: =1/(1+Assumptions!$B$10/12)^1 | G21: =1/(1+Assumptions!$B$10/12)^2 | L21: =1/(1+Assumptions!$B$10/12)^3 | Q21: =1/(1+Assumptions!$B$10/12)^4 | V21: =1/(1+Assumptions!$B$10/12)^5 | AA21: =1/(1+Assumptions!$B$10/12)^6
A22: Adjusted Cash Flow (Discounted) | B22: =B17*B21 | G22: =G17*G21 | L22: =L17*L21 | Q22: =Q17*Q21 | V22: =V17*V21 | AA22: =AA17*AA21
A23: Running Total Value (Cumulative NPV) | B23: =B22 | G23: =B23+G22 | L23: =G23+L22 | Q23: =L23+Q22 | V23: =Q23+V22 | AA23: =V23+AA22
A25: IRR helper (hidden) | B25: =-Assumptions!$B$28 | C25: =B14 | D25: =G14 | E25: =L14 | F25: =Q14 | G25: =V14 | H25: =AA14

Sheet Sensitivity
A1: What-If Scenarios (Sensitivity Analysis)
A3: PROJECT VALUE BY COST OF MONEY (DISCOUNT RATE)
A4: Cost of Money % | B4: Project Value (NPV)
A5: 0.08 | B5: =(Assumptions!$B$33+Assumptions!$B$31-Assumptions!$B$8*(Assumptions!$B$13+Assumptions!$B$14+Assumptions!$B$15+Assumptions!$B$16)/Assumptions!$B$9)/(1+0.08/12)^1+(Assumptions!$B$33-Assumptions!$B$8*(Assumptions!$B$13+Assumptions!$B$14+Assumptions!$B$15+Assumptions!$B$16)/Assumptions!$B$9)/(1+0.08/12)^2+(Assumptions!$B$33-Assumptions!$B$8*(Assumptions!$B$13+Assumptions!$B$14+Assumptions!$B$15+Assumptions!$B$16)/Assumptions!$B$9)/(1+0.08/12)^3+(Assumptions!$B$33-Assumptions!$B$8*(Assumptions!$B$13+Assumptions!$B$14+Assumptions!$B$15+Assumptions!$B$16)/Assumptions!$B$9)/(1+0.08/12)^4+(Assumptions!$B$33-Assumptions!$B$8*(Assumptions!$B$13+Assumptions!$B$14+Assumptions!$B$15+Assumptions!$B$16)/Assumptions!$B$9)/(1+0.08/12)^5+(Assumptions!$B$33+Assumptions!$B$32-Assumptions!$B$8*(Assumptions!$B$13+Assumptions!$B$14+Assumptions!$B$15+Assumptions!$B$16)/Assumptions!$B$9)/(1+0.08/12)^6
A6: 0.1 | B6: =(Assumptions!$B$33+Assumptions!$B$31-Assumptions!$B$8*(Assumptions!$B$13+Assumptions!$B$14+Assumptions!$B$15+Assumptions!$B$16)/Assumptions!$B$9)/(1+0.1/12)^1+(Assumptions!$B$33-Assumptions!$B$8*(Assumptions!$B$13+Assumptions!$B$14+Assumptions!$B$15+Assumptions!$B$16)/Assumptions!$B$9)/(1+0.1/12)^2+(Assumptions!$B$33-Assumptions!$B$8*(Assumptions!$B$13+Assumptions!$B$14+Assumptions!$B$15+Assumptions!$B$16)/Assumptions!$B$9)/(1+0.1/12)^3+(Assumptions!$B$33-Assumptions!$B$8*(Assumptions!$B$13+Assumptions!$B$14+Assumptions!$B$15+Assumptions!$B$16)/Assumptions!$B$9)/(1+0.1/12)^4+(Assumptions!$B$33-Assumptions!$B$8*(Assumptions!$B$13+Assumptions!$B$14+Assumptions!$B$15+Assumptions!$B$16)/Assumptions!$B$9)/(1+0.1/12)^5+(Assumptions!$B$33+Assumptions!$B$32-Assumptions!$B$8*(Assumptions!$B$13+Assumptions!$B$14+Assumptions!$B$15+Assumptions!$B$16)/Assumptions!$B$9)/(1+0.1/12)^6
A7: 0.12 | B7: =(Assumptions!$B$33+Assumptions!$B$31-Assumptions!$B$8*(Assumptions!$B$13+Assumptions!$B$14+Assumptions!$B$15+Assumptions!$B$16)/Assumptions!$B$9)/(1+0.12/12)^1+(Assumptions!$B$33-Assumptions!$B$8*(Assumptions!$B$13+Assumptions!$B$14+Assumptions!$B$15+Assumptions!$B$16)/Assumptions!$B$9)/(1+0.12/12)^2+(Assumptions!$B$33-Assumptions!$B$8*(Assumptions!$B$13+Assumptions!$B$14+Assumptions!$B$15+Assumptions!$B$16)/Assumptions!$B$9)/(1+0.12/12)^3+(Assumptions!$B$33-Assumptions!$B$8*(Assumptions!$B$13+Assumptions!$B$14+Assumptions!$B$15+Assumptions!$B$16)/Assumptions!$B$9)/(1+0.12/12)^4+(Assumptions!$B$33-Assumptions!$B$8*(Assumptions!$B$13+Assumptions!$B$14+Assumptions!$B$15+Assumptions!$B$16)/Assumptions!$B$9)/(1+0.12/12)^5+(Assumptions!$B$33+Assumptions!$B$32-Assumptions!$B$8*(Assumptions!$B$13+Assumptions!$B$14+Assumptions!$B$15+Assumptions!$B$16)/Assumptions!$B$9)/(1+0.12/12)^6
A8: 0.14 | B8: =(Assumptions!$B$33+Assumptions!$B$31-Assumptions!$B$8*(Assumptions!$B$13+Assumptions!$B$14+Assumptions!$B$15+Assumptions!$B$16)/Assumptions!$B$9)/(1+0.14/12)^1+(Assumptions!$B$33-Assumptions!$B$8*(Assumptions!$B$13+Assumptions!$B$14+Assumptions!$B$15+Assumptions!$B$16)/Assumptions!$B$9)/(1+0.14/12)^2+(Assumptions!$B$33-Assumptions!$B$8*(Assumptions!$B$13+Assumptions!$B$14+Assumptions!$B$15+Assumptions!$B$16)/Assumptions!$B$9)/(1+0.14/12)^3+(Assumptions!$B$33-Assumptions!$B$8*(Assumptions!$B$13+Assumptions!$B$14+Assumptions!$B$15+Assumptions!$B$16)/Assumptions!$B$9)/(1+0.14/12)^4+(Assumptions!$B$33-Assumptions!$B$8*(Assumptions!$B$13+Assumptions!$B$14+Assumptions!$B$15+Assumptions!$B$16)/Assumptions!$B$9)/(1+0.14/12)^5+(Assumptions!$B$33+Assumptions!$B$32-Assumptions!$B$8*(Assumptions!$B$13+Assumptions!$B$14+Assumptions!$B$15+Assumptions!$B$16)/Assumptions!$B$9)/(1+0.14/12)^6
A9: 0.16 | B9: =(Assumptions!$B$33+Assumptions!$B$31-Assumptions!$B$8*(Assumptions!$B$13+Assumptions!$B$14+Assumptions!$B$15+Assumptions!$B$16)/Assumptions!$B$9)/(1+0.16/12)^1+(Assumptions!$B$33-Assumptions!$B$8*(Assumptions!$B$13+Assumptions!$B$14+Assumptions!$B$15+Assumptions!$B$16)/Assumptions!$B$9)/(1+0.16/12)^2+(Assumptions!$B$33-Assumptions!$B$8*(Assumptions!$B$13+Assumptions!$B$14+Assumptions!$B$15+Assumptions!$B$16)/Assumptions!$B$9)/(1+0.16/12)^3+(Assumptions!$B$33-Assumptions!$B$8*(Assumptions!$B$13+Assumptions!$B$14+Assumptions!$B$15+Assumptions!$B$16)/Assumptions!$B$9)/(1+0.16/12)^4+(Assumptions!$B$33-Assumptions!$B$8*(Assumptions!$B$13+Assumptions!$B$14+Assumptions!$B$15+Assumptions!$B$16)/Assumptions!$B$9)/(1+0.16/12)^5+(Assumptions!$B$33+Assumptions!$B$32-Assumptions!$B$8*(Assumptions!$B$13+Assumptions!$B$14+Assumptions!$B$15+Assumptions!$B$16)/Assumptions!$B$9)/(1+0.16/12)^6
A12: PROJECT VALUE BY LABOR COST x TIMELINE
A13: Labor \ Timeline | B13: =Assumptions!$B$9+-2&"mo" | C13: =Assumptions!$B$9+-1&"mo" | D13: =Assumptions!$B$9&"mo (base)" | E13: =Assumptions!$B$9+1&"mo" | F13: =Assumptions!$B$9+2&"mo"
A14: =Assumptions!$B$13*(1+-0.2) | B14: =Assumptions!$B$8*Assumptions!$B$19+(Assumptions!$B$8/(MAX(1,Assumptions!$B$9+-2))*(1-Assumptions!$B$19-Assumptions!$B$20)-Assumptions!$B$8*(Assumptions!$B$13*(1+-0.2)+Assumptions!$B$14+Assumptions!$B$15+Assumptions!$B$16)/(MAX(1,Assumptions!$B$9+-2)))*(1-(1+Assumptions!$B$10/12)^-(MAX(1,Assumptions!$B$9+-2)))/(Assumptions!$B$10/12)+Assumptions!$B$8*Assumptions!$B$20/(1+Assumptions!$B$10/12)^(MAX(1,Assumptions!$B$9+-2)) | C14: =Assumptions!$B$8*Assumptions!$B$19+(Assumptions!$B$8/(MAX(1,Assumptions!$B$9+-1))*(1-Assumptions!$B$19-Assumptions!$B$20)-Assumptions!$B$8*(Assumptions!$B$13*(1+-0.2)+Assumptions!$B$14+Assumptions!$B$15+Assumptions!$B$16)/(MAX(1,Assumptions!$B$9+-1)))*(1-(1+Assumptions!$B$10/12)^-(MAX(1,Assumptions!$B$9+-1)))/(Assumptions!$B$10/12)+Assumptions!$B$8*Assumptions!$B$20/(1+Assumptions!$B$10/12)^(MAX(1,Assumptions!$B$9+-1)) | D14: =Assumptions!$B$8*Assumptions!$B$19+(Assumptions!$B$8/(MAX(1,Assumptions!$B$9+0))*(1-Assumptions!$B$19-Assumptions!$B$20)-Assumptions!$B$8*(Assumptions!$B$13*(1+-0.2)+Assumptions!$B$14+Assumptions!$B$15+Assumptions!$B$16)/(MAX(1,Assumptions!$B$9+0)))*(1-(1+Assumptions!$B$10/12)^-(MAX(1,Assumptions!$B$9+0)))/(Assumptions!$B$10/12)+Assumptions!$B$8*Assumptions!$B$20/(1+Assumptions!$B$10/12)^(MAX(1,Assumptions!$B$9+0)) | E14: =Assumptions!$B$8*Assumptions!$B$19+(Assumptions!$B$8/(MAX(1,Assumptions!$B$9+1))*(1-Assumptions!$B$19-Assumptions!$B$20)-Assumptions!$B$8*(Assumptions!$B$13*(1+-0.2)+Assumptions!$B$14+Assumptions!$B$15+Assumptions!$B$16)/(MAX(1,Assumptions!$B$9+1)))*(1-(1+Assumptions!$B$10/12)^-(MAX(1,Assumptions!$B$9+1)))/(Assumptions!$B$10/12)+Assumptions!$B$8*Assumptions!$B$20/(1+Assumptions!$B$10/12)^(MAX(1,Assumptions!$B$9+1)) | F14: =Assumptions!$B$8*Assumptions!$B$19+(Assumptions!$B$8/(MAX(1,Assumptions!$B$9+2))*(1-Assumptions!$B$19-Assumptions!$B$20)-Assumptions!$B$8*(Assumptions!$B$13*(1+-0.2)+Assumptions!$B$14+Assumptions!$B$15+Assumptions!$B$16)/(MAX(1,Assumptions!$B$9+2)))*(1-(1+Assumptions!$B$10/12)^-(MAX(1,Assumptions!$B$9+2)))/(Assumptions!$B$10/12)+Assumptions!$B$8*Assumptions!$B$20/(1+Assumptions!$B$10/12)^(MAX(1,Assumptions!$B$9+2))
A15: =Assumptions!$B$13*(1+-0.1) | B15: =Assumptions!$B$8*Assumptions!$B$19+(Assumptions!$B$8/(MAX(1,Assumptions!$B$9+-2))*(1-Assumptions!$B$19-Assumptions!$B$20)-Assumptions!$B$8*(Assumptions!$B$13*(1+-0.1)+Assumptions!$B$14+Assumptions!$B$15+Assumptions!$B$16)/(MAX(1,Assumptions!$B$9+-2)))*(1-(1+Assumptions!$B$10/12)^-(MAX(1,Assumptions!$B$9+-2)))/(Assumptions!$B$10/12)+Assumptions!$B$8*Assumptions!$B$20/(1+Assumptions!$B$10/12)^(MAX(1,Assumptions!$B$9+-2)) | C15: =Assumptions!$B$8*Assumptions!$B$19+(Assumptions!$B$8/(MAX(1,Assumptions!$B$9+-1))*(1-Assumptions!$B$19-Assumptions!$B$20)-Assumptions!$B$8*(Assumptions!$B$13*(1+-0.1)+Assumptions!$B$14+Assumptions!$B$15+Assumptions!$B$16)/(MAX(1,Assumptions!$B$9+-1)))*(1-(1+Assumptions!$B$10/12)^-(MAX(1,Assumptions!$B$9+-1)))/(Assumptions!$B$10/12)+Assumptions!$B$8*Assumptions!$B$20/(1+Assumptions!$B$10/12)^(MAX(1,Assumptions!$B$9+-1)) | D15: =Assumptions!$B$8*Assumptions!$B$19+(Assumptions!$B$8/(MAX(1,Assumptions!$B$9+0))*(1-Assumptions!$B$19-Assumptions!$B$20)-Assumptions!$B$8*(Assumptions!$B$13*(1+-0.1)+Assumptions!$B$14+Assumptions!$B$15+Assumptions!$B$16)/(MAX(1,Assumptions!$B$9+0)))*(1-(1+Assumptions!$B$10/12)^-(MAX(1,Assumptions!$B$9+0)))/(Assumptions!$B$10/12)+Assumptions!$B$8*Assumptions!$B$20/(1+Assumptions!$B$10/12)^(MAX(1,Assumptions!$B$9+0)) | E15: =Assumptions!$B$8*Assumptions!$B$19+(Assumptions!$B$8/(MAX(1,Assumptions!$B$9+1))*(1-Assumptions!$B$19-Assumptions!$B$20)-Assumptions!$B$8*(Assumptions!$B$13*(1+-0.1)+Assumptions!$B$14+Assumptions!$B$15+Assumptions!$B$16)/(MAX(1,Assumptions!$B$9+1)))*(1-(1+Assumptions!$B$10/12)^-(MAX(1,Assumptions!$B$9+1)))/(Assumptions!$B$10/12)+Assumptions!$B$8*Assumptions!$B$20/(1+Assumptions!$B$10/12)^(MAX(1,Assumptions!$B$9+1)) | F15: =Assumptions!$B$8*Assumptions!$B$19+(Assumptions!$B$8/(MAX(1,Assumptions!$B$9+2))*(1-Assumptions!$B$19-Assumptions!$B$20)-Assumptions!$B$8*(Assumptions!$B$13*(1+-0.1)+Assumptions!$B$14+Assumptions!$B$15+Assumptions!$B$16)/(MAX(1,Assumptions!$B$9+2)))*(1-(1+Assumptions!$B$10/12)^-(MAX(1,Assumptions!$B$9+2)))/(Assumptions!$B$10/12)+Assumptions!$B$8*Assumptions!$B$20/(1+Assumptions!$B$10/12)^(MAX(1,Assumptions!$B$9+2))
A16: =Assumptions!$B$13 | B16: =Assumptions!$B$8*Assumptions!$B$19+(Assumptions!$B$8/(MAX(1,Assumptions!$B$9+-2))*(1-Assumptions!$B$19-Assumptions!$B$20)-Assumptions!$B$8*(Assumptions!$B$13+Assumptions!$B$14+Assumptions!$B$15+Assumptions!$B$16)/(MAX(1,Assumptions!$B$9+-2)))*(1-(1+Assumptions!$B$10/12)^-(MAX(1,Assumptions!$B$9+-2)))/(Assumptions!$B$10/12)+Assumptions!$B$8*Assumptions!$B$20/(1+Assumptions!$B$10/12)^(MAX(1,Assumptions!$B$9+-2)) | C16: =Assumptions!$B$8*Assumptions!$B$19+(Assumptions!$B$8/(MAX(1,Assumptions!$B$9+-1))*(1-Assumptions!$B$19-Assumptions!$B$20)-Assumptions!$B$8*(Assumptions!$B$13+Assumptions!$B$14+Assumptions!$B$15+Assumptions!$B$16)/(MAX(1,Assumptions!$B$9+-1)))*(1-(1+Assumptions!$B$10/12)^-(MAX(1,Assumptions!$B$9+-1)))/(Assumptions!$B$10/12)+Assumptions!$B$8*Assumptions!$B$20/(1+Assumptions!$B$10/12)^(MAX(1,Assumptions!$B$9+-1)) | D16: =Assumptions!$B$8*Assumptions!$B$19+(Assumptions!$B$8/(MAX(1,Assumptions!$B$9+0))*(1-Assumptions!$B$19-Assumptions!$B$20)-Assumptions!$B$8*(Assumptions!$B$13+Assumptions!$B$14+Assumptions!$B$15+Assumptions!$B$16)/(MAX(1,Assumptions!$B$9+0)))*(1-(1+Assumptions!$B$10/12)^-(MAX(1,Assumptions!$B$9+0)))/(Assumptions!$B$10/12)+Assumptions!$B$8*Assumptions!$B$20/(1+Assumptions!$B$10/12)^(MAX(1,Assumptions!$B$9+0)) | E16: =Assumptions!$B$8*Assumptions!$B$19+(Assumptions!$B$8/(MAX(1,Assumptions!$B$9+1))*(1-Assumptions!$B$19-Assumptions!$B$20)-Assumptions!$B$8*(Assumptions!$B$13+Assumptions!$B$14+Assumptions!$B$15+Assumptions!$B$16)/(MAX(1,Assumptions!$B$9+1)))*(1-(1+Assumptions!$B$10/12)^-(MAX(1,Assumptions!$B$9+1)))/(Assumptions!$B$10/12)+Assumptions!$B$8*Assumptions!$B$20/(1+Assumptions!$B$10/12)^(MAX(1,Assumptions!$B$9+1)) | F16: =Assumptions!$B$8*Assumptions!$B$19+(Assumptions!$B$8/(MAX(1,Assumptions!$B$9+2))*(1-Assumptions!$B$19-Assumptions!$B$20)-Assumptions!$B$8*(Assumptions!$B$13+Assumptions!$B$14+Assumptions!$B$15+Assumptions!$B$16)/(MAX(1,Assumptions!$B$9+2)))*(1-(1+Assumptions!$B$10/12)^-(MAX(1,Assumptions!$B$9+2)))/(Assumptions!$B$10/12)+Assumptions!$B$8*Assumptions!$B$20/(1+Assumptions!$B$10/12)^(MAX(1,Assumptions!$B$9+2))
A17: =Assumptions!$B$13*(1+0.1) | B17: =Assumptions!$B$8*Assumptions!$B$19+(Assumptions!$B$8/(MAX(1,Assumptions!$B$9+-2))*(1-Assumptions!$B$19-Assumptions!$B$20)-Assumptions!$B$8*(Assumptions!$B$13*(1+0.1)+Assumptions!$B$14+Assumptions!$B$15+Assumptions!$B$16)/(MAX(1,Assumptions!$B$9+-2)))*(1-(1+Assumptions!$B$10/12)^-(MAX(1,Assumptions!$B$9+-2)))/(Assumptions!$B$10/12)+Assumptions!$B$8*Assumptions!$B$20/(1+Assumptions!$B$10/12)^(MAX(1,Assumptions!$B$9+-2)) | C17: =Assumptions!$B$8*Assumptions!$B$19+(Assumptions!$B$8/(MAX(1,Assumptions!$B$9+-1))*(1-Assumptions!$B$19-Assumptions!$B$20)-Assumptions!$B$8*(Assumptions!$B$13*(1+0.1)+Assumptions!$B$14+Assumptions!$B$15+Assumptions!$B$16)/(MAX(1,Assumptions!$B$9+-1)))*(1-(1+Assumptions!$B$10/12)^-(MAX(1,Assumptions!$B$9+-1)))/(Assumptions!$B$10/12)+Assumptions!$B$8*Assumptions!$B$20/(1+Assumptions!$B$10/12)^(MAX(1,Assumptions!$B$9+-1)) | D17: =Assumptions!$B$8*Assumptions!$B$19+(Assumptions!$B$8/(MAX(1,Assumptions!$B$9+0))*(1-Assumptions!$B$19-Assumptions!$B$20)-Assumptions!$B$8*(Assumptions!$B$13*(1+0.1)+Assumptions!$B$14+Assumptions!$B$15+Assumptions!$B$16)/(MAX(1,Assumptions!$B$9+0)))*(1-(1+Assumptions!$B$10/12)^-(MAX(1,Assumptions!$B$9+0)))/(Assumptions!$B$10/12)+Assumptions!$B$8*Assumptions!$B$20/(1+Assumptions!$B$10/12)^(MAX(1,Assumptions!$B$9+0)) | E17: =Assumptions!$B$8*Assumptions!$B$19+(Assumptions!$B$8/(MAX(1,Assumptions!$B$9+1))*(1-Assumptions!$B$19-Assumptions!$B$20)-Assumptions!$B$8*(Assumptions!$B$13*(1+0.1)+Assumptions!$B$14+Assumptions!$B$15+Assumptions!$B$16)/(MAX(1,Assumptions!$B$9+1)))*(1-(1+Assumptions!$B$10/12)^-(MAX(1,Assumptions!$B$9+1)))/(Assumptions!$B$10/12)+Assumptions!$B$8*Assumptions!$B$20/(1+Assumptions!$B$10/12)^(MAX(1,Assumptions!$B$9+1)) | F17: =Assumptions!$B$8*Assumptions!$B$19+(Assumptions!$B$8/(MAX(1,Assumptions!$B$9+2))*(1-Assumptions!$B$19-Assumptions!$B$20)-Assumptions!$B$8*(Assumptions!$B$13*(1+0.1)+Assumptions!$B$14+Assumptions!$B$15+Assumptions!$B$16)/(MAX(1,Assumptions!$B$9+2)))*(1-(1+Assumptions!$B$10/12)^-(MAX(1,Assumptions!$B$9+2)))/(Assumptions!$B$10/12)+Assumptions!$B$8*Assumptions!$B$20/(1+Assumptions!$B$10/12)^(MAX(1,Assumptions!$B$9+2))
A18: =Assumptions!$B$13*(1+0.2) | B18: =Assumptions!$B$8*Assumptions!$B$19+(Assumptions!$B$8/(MAX(1,Assumptions!$B$9+-2))*(1-Assumptions!$B$19-Assumptions!$B$20)-Assumptions!$B$8*(Assumptions!$B$13*(1+0.2)+Assumptions!$B$14+Assumptions!$B$15+Assumptions!$B$16)/(MAX(1,Assumptions!$B$9+-2)))*(1-(1+Assumptions!$B$10/12)^-(MAX(1,Assumptions!$B$9+-2)))/(Assumptions!$B$10/12)+Assumptions!$B$8*Assumptions!$B$20/(1+Assumptions!$B$10/12)^(MAX(1,Assumptions!$B$9+-2)) | C18: =Assumptions!$B$8*Assumptions!$B$19+(Assumptions!$B$8/(MAX(1,Assumptions!$B$9+-1))*(1-Assumptions!$B$19-Assumptions!$B$20)-Assumptions!$B$8*(Assumptions!$B$13*(1+0.2)+Assumptions!$B$14+Assumptions!$B$15+Assumptions!$B$16)/(MAX(1,Assumptions!$B$9+-1)))*(1-(1+Assumptions!$B$10/12)^-(MAX(1,Assumptions!$B$9+-1)))/(Assumptions!$B$10/12)+Assumptions!$B$8*Assumptions!$B$20/(1+Assumptions!$B$10/12)^(MAX(1,Assumptions!$B$9+-1)) | D18: =Assumptions!$B$8*Assumptions!$B$19+(Assumptions!$B$8/(MAX(1,Assumptions!$B$9+0))*(1-Assumptions!$B$19-Assumptions!$B$20)-Assumptions!$B$8*(Assumptions!$B$13*(1+0.2)+Assumptions!$B$14+Assumptions!$B$15+Assumptions!$B$16)/(MAX(1,Assumptions!$B$9+0)))*(1-(1+Assumptions!$B$10/12)^-(MAX(1,Assumptions!$B$9+0)))/(Assumptions!$B$10/12)+Assumptions!$B$8*Assumptions!$B$20/(1+Assumptions!$B$10/12)^(MAX(1,Assumptions!$B$9+0)) | E18: =Assumptions!$B$8*Assumptions!$B$19+(Assumptions!$B$8/(MAX(1,Assumptions!$B$9+1))*(1-Assumptions!$B$19-Assumptions!$B$20)-Assumptions!$B$8*(Assumptions!$B$13*(1+0.2)+Assumptions!$B$14+Assumptions!$B$15+Assumptions!$B$16)/(MAX(1,Assumptions!$B$9+1)))*(1-(1+Assumptions!$B$10/12)^-(MAX(1,Assumptions!$B$9+1)))/(Assumptions!$B$10/12)+Assumptions!$B$8*Assumptions!$B$20/(1+Assumptions!$B$10/12)^(MAX(1,Assumptions!$B$9+1)) | F18: =Assumptions!$B$8*Assumptions!$B$19+(Assumptions!$B$8/(MAX(1,Assumptions!$B$9+2))*(1-Assumptions!$B$19-Assumptions!$B$20)-Assumptions!$B$8*(Assumptions!$B$13*(1+0.2)+Assumptions!$B$14+Assumptions!$B$15+Assumptions!$B$16)/(MAX(1,Assumptions!$B$9+2)))*(1-(1+Assumptions!$B$10/12)^-(MAX(1,Assumptions!$B$9+2)))/(Assumptions!$B$10/12)+Assumptions!$B$8*Assumptions!$B$20/(1+Assumptions!$B$10/12)^(MAX(1,Assumptions!$B$9+2))
